{
  "_python_requires": ">=3.9",
  "edges": [
    {
      "fromNode": 0,
      "requirement": ">=2.1.1",
      "toNode": 1
    }
  ],
  "error": "",
  "nodes": [
    {
      "bundled": false,
      "errors": [],
      "relation": "SELF",
      "versionKey": {
        "name": "werkzeug",
        "system": "PYPI",
        "version": "3.1.8"
      }
    },
    {
      "bundled": false,
      "errors": [],
      "relation": "DIRECT",
      "versionKey": {
        "name": "markupsafe",
        "system": "PYPI",
        "version": "3.0.3"
      }
    }
  ]
}
